moltemplate/__init__.py
moltemplate/amber2lt.py
moltemplate/bonds_by_type.py
moltemplate/charge_by_bond.py
moltemplate/dump2data.py
moltemplate/ettree.py
moltemplate/ettree_styles.py
moltemplate/extract_espresso_atom_types.py
moltemplate/extract_lammps_data.py
moltemplate/genpoly_lt.py
moltemplate/genpoly_modify_lt.py
moltemplate/interpolate_curve.py
moltemplate/ltemplify.py
moltemplate/lttree.py
moltemplate/lttree_check.py
moltemplate/lttree_postprocess.py
moltemplate/lttree_styles.py
moltemplate/mol22lt.py
moltemplate/nbody_Angles.py
moltemplate/nbody_Bonds.py
moltemplate/nbody_Dihedrals.py
moltemplate/nbody_Impropers.py
moltemplate/nbody_by_type.py
moltemplate/nbody_by_type_lib.py
moltemplate/nbody_fix_ttree_assignments.py
moltemplate/nbody_graph_search.py
moltemplate/nbody_reorder_atoms.py
moltemplate/ordereddict.py
moltemplate/pdbsort.py
moltemplate/postprocess_coeffs.py
moltemplate/postprocess_input_script.py
moltemplate/postprocess_transitions.py
moltemplate/raw2data.py
moltemplate/recenter_coords.py
moltemplate/remove_duplicate_atoms.py
moltemplate/remove_duplicates_nbody.py
moltemplate/renumber_DATA_first_column.py
moltemplate/ttree.py
moltemplate/ttree_lex.py
moltemplate/ttree_matrix_stack.py
moltemplate/ttree_render.py
moltemplate/force_fields/compass_published.lt
moltemplate/force_fields/cooke_deserno_lipid.lt
moltemplate/force_fields/dreiding.lt
moltemplate/force_fields/drymartini.lt
moltemplate/force_fields/gaff.lt
moltemplate/force_fields/gaff2.lt
moltemplate/force_fields/graphene.lt
moltemplate/force_fields/graphene_rectangular.lt
moltemplate/force_fields/graphite.lt
moltemplate/force_fields/loplsaa.lt
moltemplate/force_fields/loplsaa2008.lt
moltemplate/force_fields/loplsaa2024.lt
moltemplate/force_fields/martini.lt
moltemplate/force_fields/oplsaa.lt
moltemplate/force_fields/oplsaa2008.lt
moltemplate/force_fields/oplsaa2024.lt
moltemplate/force_fields/sdk.lt
moltemplate/force_fields/spc_oplsaa.lt
moltemplate/force_fields/spc_oplsaa2008.lt
moltemplate-2.22.5.dist-info/LICENSE.md
moltemplate-2.22.5.dist-info/METADATA
moltemplate-2.22.5.dist-info/WHEEL
moltemplate-2.22.5.dist-info/entry_points.txt
moltemplate-2.22.5.dist-info/top_level.txt
moltemplate-2.22.5.dist-info/zip-safe
moltemplate-2.22.5.dist-info/RECORD
