Metadata-Version: 2.2
Name: moltemplate
Version: 2.22.5
Summary: A general cross-platform text-based molecule builder for LAMMPS
Home-page: https://github.com/jewettaij/moltemplate
Download-URL: https://github.com/jewettaij/moltemplate/archive/v2.22.5.zip
Author: Andrew Jewett
Author-email: jewett.aij@gmail.com
License: MIT
Keywords: simulation,LAMMPS,molecule editor,molecule builder,ESPResSo
Classifier: Environment :: Console
Classifier: License :: OSI Approved :: MIT License
Classifier: Operating System :: MacOS :: MacOS X
Classifier: Operating System :: POSIX :: Linux
Classifier: Operating System :: Microsoft :: Windows
Classifier: Programming Language :: Python
Classifier: Programming Language :: Python :: 3.4
Classifier: Programming Language :: Unix Shell
Classifier: Topic :: Scientific/Engineering :: Chemistry
Classifier: Topic :: Scientific/Engineering :: Physics
Classifier: Topic :: Multimedia :: Graphics :: 3D Modeling
Classifier: Intended Audience :: Science/Research
License-File: LICENSE.md
Requires-Dist: numpy
Dynamic: author
Dynamic: author-email
Dynamic: classifier
Dynamic: description
Dynamic: download-url
Dynamic: home-page
Dynamic: keywords
Dynamic: license
Dynamic: requires-dist
Dynamic: summary
